{
  "description": "Subnet contains resolved Subnet selector values utilized for node launch",
  "type": "object",
  "required": [
    "id",
    "zone"
  ],
  "properties": {
    "id": {
      "description": "ID of the subnet",
      "type": [
        "string",
        "null"
      ],
      "default": ""
    },
    "zone": {
      "description": "The associated availability zone",
      "type": [
        "string",
        "null"
      ],
      "default": ""
    }
  },
  "additionalProperties": false,
  "$schema": "http://json-schema.org/schema#"
}