{
  "description": "X509Subject Full X509 name specification",
  "type": "object",
  "properties": {
    "countries": {
      "description": "Countries to be used on the Certificate.",
      "type": [
        "array",
        "null"
      ],
      "items": {
        "type": [
          "string",
          "null"
        ],
        "default": ""
      },
      "x-kubernetes-list-type": "atomic"
    },
    "localities": {
      "description": "Cities to be used on the Certificate.",
      "type": [
        "array",
        "null"
      ],
      "items": {
        "type": [
          "string",
          "null"
        ],
        "default": ""
      },
      "x-kubernetes-list-type": "atomic"
    },
    "organizationalUnits": {
      "description": "Organizational Units to be used on the Certificate.",
      "type": [
        "array",
        "null"
      ],
      "items": {
        "type": [
          "string",
          "null"
        ],
        "default": ""
      },
      "x-kubernetes-list-type": "atomic"
    },
    "organizations": {
      "description": "Organizations to be used on the Certificate.",
      "type": [
        "array",
        "null"
      ],
      "items": {
        "type": [
          "string",
          "null"
        ],
        "default": ""
      },
      "x-kubernetes-list-type": "atomic"
    },
    "postalCodes": {
      "description": "Postal codes to be used on the Certificate.",
      "type": [
        "array",
        "null"
      ],
      "items": {
        "type": [
          "string",
          "null"
        ],
        "default": ""
      },
      "x-kubernetes-list-type": "atomic"
    },
    "provinces": {
      "description": "State/Provinces to be used on the Certificate.",
      "type": [
        "array",
        "null"
      ],
      "items": {
        "type": [
          "string",
          "null"
        ],
        "default": ""
      },
      "x-kubernetes-list-type": "atomic"
    },
    "serialNumber": {
      "description": "Serial number to be used on the Certificate.",
      "type": [
        "string",
        "null"
      ]
    },
    "streetAddresses": {
      "description": "Street addresses to be used on the Certificate.",
      "type": [
        "array",
        "null"
      ],
      "items": {
        "type": [
          "string",
          "null"
        ],
        "default": ""
      },
      "x-kubernetes-list-type": "atomic"
    }
  },
  "additionalProperties": false,
  "$schema": "http://json-schema.org/schema#"
}